sparkle_session/__init__.py
sparkle_session/create_table.py
sparkle_session/dataframe.py
sparkle_session/session.py
sparkle_session/spark_and_log.py
sparkle_session/spark_logger.py
sparkle_session/struct_type.py
sparkle_session/utils.py
sparkle_session-1.3.0.dist-info/LICENSE
sparkle_session-1.3.0.dist-info/WHEEL
sparkle_session-1.3.0.dist-info/METADATA
sparkle_session-1.3.0.dist-info/RECORD
