Metadata-Version: 2.1
Name: sparkle-session
Version: 1.3.0
Summary: Common patterns and often used code from dozens of pyspark projects available at your fingertips
License: GPL-3.0-or-later
Author: Machiel Keizer Groeneveld
Requires-Python: >=3.7.1,<4
Classifier: License :: OSI Approved :: GNU General Public License v3 or later (GPLv3+)
Classifier: Programming Language :: Python :: 3
Classifier: Programming Language :: Python :: 3.10
Classifier: Programming Language :: Python :: 3.8
Classifier: Programming Language :: Python :: 3.9
